proletract/__init__.py
proletract/backend/__init__.py
proletract/backend/main.py
proletract/backend/requirements.txt
proletract/backend/data/pathogenic_TRs.bed
proletract/cli/__init__.py
proletract/cli/main.py
proletract/frontend/package-lock.json
proletract/frontend/package.json
proletract/frontend/tsconfig.json
proletract/frontend/build/ProleTRact_logo.svg
proletract/frontend/build/asset-manifest.json
proletract/frontend/build/index.html
proletract/frontend/build/intro_logo.mp4
proletract/frontend/build/static/css/main.98b5de2b.css
proletract/frontend/build/static/css/main.98b5de2b.css.map
proletract/frontend/build/static/js/239.2c8718d1.chunk.js
proletract/frontend/build/static/js/239.2c8718d1.chunk.js.LICENSE.txt
proletract/frontend/build/static/js/239.2c8718d1.chunk.js.map
proletract/frontend/build/static/js/main.c6a14d5c.js
proletract/frontend/build/static/js/main.c6a14d5c.js.LICENSE.txt
proletract/frontend/build/static/js/main.c6a14d5c.js.map
proletract/frontend/public/ProleTRact_logo.svg
proletract/frontend/public/index.html
proletract/frontend/public/intro_logo.mp4
proletract/frontend/src/App.css
proletract/frontend/src/App.tsx
proletract/frontend/src/index.css
proletract/frontend/src/index.tsx
proletract/frontend/src/types.ts
proletract/frontend/src/components/AnnotationPanel.css
proletract/frontend/src/components/AnnotationPanel.tsx
proletract/frontend/src/components/BookmarksPanel.css
proletract/frontend/src/components/BookmarksPanel.tsx
proletract/frontend/src/components/CohortAnalysis.tsx
proletract/frontend/src/components/CohortModeView.tsx
proletract/frontend/src/components/ExportMenu.css
proletract/frontend/src/components/ExportMenu.tsx
proletract/frontend/src/components/ExternalLinksPanel.css
proletract/frontend/src/components/ExternalLinksPanel.tsx
proletract/frontend/src/components/FeaturesPage.css
proletract/frontend/src/components/FeaturesPage.tsx
proletract/frontend/src/components/FloatingNavigation.css
proletract-1.0.1.dist-info/licenses/LICENSE
proletract-1.0.1.dist-info/METADATA
proletract-1.0.1.dist-info/WHEEL
proletract-1.0.1.dist-info/entry_points.txt
proletract-1.0.1.dist-info/top_level.txt
proletract-1.0.1.dist-info/zip-safe
proletract-1.0.1.dist-info/RECORD
