Metadata-Version: 2.4
Name: proletract
Version: 1.0.1
Summary: ProleTRact - Tandem Repeat Visualization Tool
Home-page: https://github.com/Lionward/ProleTRact
Author: Lion Ward Al Raei
Author-email: Lion Ward Al Raei <lionward.alraei@gmail.com>
Project-URL: Homepage, https://github.com/Lionward/ProleTRact
Project-URL: Repository, https://github.com/Lionward/ProleTRact
Project-URL: Bug Tracker, https://github.com/Lionward/ProleTRact/issues
Keywords: tandem repeat,VCF,visualization,bioinformatics,genomics
Classifier: Development Status :: 4 - Beta
Classifier: Intended Audience :: Science/Research
Classifier: Topic :: Scientific/Engineering :: Bio-Informatics
Classifier: Programming Language :: Python :: 3
Classifier: Programming Language :: Python :: 3.9
Classifier: Programming Language :: Python :: 3.10
Classifier: Programming Language :: Python :: 3.11
Requires-Python: >=3.9
License-File: LICENSE
Requires-Dist: fastapi>=0.104.0
Requires-Dist: uvicorn[standard]>=0.24.0
Requires-Dist: pysam>=0.22
Requires-Dist: pydantic>=2.0
Requires-Dist: python-multipart>=0.0.6
Dynamic: author
Dynamic: home-page
Dynamic: license-file
Dynamic: requires-python
